{
  "status": "Success",
  "code": 200,
  "author": "Zeltoria",
  "data": {
    "ok": true,
    "id": 406924,
    "title": {
      "english": "The island of Tanned Milfs-I started an auntie guesthouse",
      "japanese": "[ぜんまいこうろぎ] その島は真っ黒に日焼けしたおばさんたちの性息地である <おばちゃん民宿をはじめました> [英訳]",
      "pretty": "The island of Tanned Milfs-I started an auntie guesthouse"
    },
    "images": {
      "cover": {
        "t": "https://c.kontol.online/api/imageV2/t/2246211/thumb.jpg",
        "w": 350,
        "h": 525
      },
      "pages": [
        {
          "t": "https://a.kontol.online/api/imageV2/i/2246211/1.jpg",
          "w": 1280,
          "h": 1920
        },
        {
          "t": "https://b.kontol.online/api/imageV2/i/2246211/2.jpg",
          "w": 1280,
          "h": 1920
        },
        {
          "t": "https://c.kontol.online/api/imageV2/i/2246211/3.jpg",
          "w": 1280,
          "h": 1920
        },
        {
          "t": "https://d.kontol.online/api/imageV2/i/2246211/4.jpg",
          "w": 1280,
          "h": 1920
        },
        {
          "t": "https://a.kontol.online/api/imageV2/i/2246211/5.jpg",
          "w": 1280,
          "h": 1920
        },
        {
          "t": "https://b.kontol.online/api/imageV2/i/2246211/6.jpg",
          "w": 1280,
          "h": 1920
        },
        {
          "t": "https://c.kontol.online/api/imageV2/i/2246211/7.jpg",
          "w": 1280,
          "h": 1920
        },
        {
          "t": "https://d.kontol.online/api/imageV2/i/2246211/8.jpg",
          "w": 1280,
          "h": 1920
        },
        {
          "t": "https://a.kontol.online/api/imageV2/i/2246211/9.jpg",
          "w": 1280,
          "h": 1920
        },
        {
          "t": "https://b.kontol.online/api/imageV2/i/2246211/10.jpg",
          "w": 1280,
          "h": 1920
        },
        {
          "t": "https://c.kontol.online/api/imageV2/i/2246211/11.jpg",
          "w": 1280,
          "h": 1920
        },
        {
          "t": "https://d.kontol.online/api/imageV2/i/2246211/12.jpg",
          "w": 1280,
          "h": 1920
        },
        {
          "t": "https://a.kontol.online/api/imageV2/i/2246211/13.jpg",
          "w": 1280,
          "h": 1920
        },
        {
          "t": "https://b.kontol.online/api/imageV2/i/2246211/14.jpg",
          "w": 1280,
          "h": 1920
        },
        {
          "t": "https://c.kontol.online/api/imageV2/i/2246211/15.jpg",
          "w": 1280,
          "h": 1920
        },
        {
          "t": "https://d.kontol.online/api/imageV2/i/2246211/16.jpg",
          "w": 1280,
          "h": 1920
        },
        {
          "t": "https://a.kontol.online/api/imageV2/i/2246211/17.jpg",
          "w": 1280,
          "h": 1920
        },
        {
          "t": "https://b.kontol.online/api/imageV2/i/2246211/18.jpg",
          "w": 1280,
          "h": 1920
        },
        {
          "t": "https://c.kontol.online/api/imageV2/i/2246211/19.jpg",
          "w": 1280,
          "h": 1920
        },
        {
          "t": "https://d.kontol.online/api/imageV2/i/2246211/20.jpg",
          "w": 1280,
          "h": 1920
        },
        {
          "t": "https://a.kontol.online/api/imageV2/i/2246211/21.jpg",
          "w": 1280,
          "h": 1920
        },
        {
          "t": "https://b.kontol.online/api/imageV2/i/2246211/22.jpg",
          "w": 1280,
          "h": 1920
        },
        {
          "t": "https://c.kontol.online/api/imageV2/i/2246211/23.jpg",
          "w": 1280,
          "h": 1920
        },
        {
          "t": "https://d.kontol.online/api/imageV2/i/2246211/24.jpg",
          "w": 1280,
          "h": 1920
        },
        {
          "t": "https://a.kontol.online/api/imageV2/i/2246211/25.jpg",
          "w": 1280,
          "h": 1920
        },
        {
          "t": "https://b.kontol.online/api/imageV2/i/2246211/26.jpg",
          "w": 1280,
          "h": 1920
        },
        {
          "t": "https://c.kontol.online/api/imageV2/i/2246211/27.jpg",
          "w": 1280,
          "h": 1920
        },
        {
          "t": "https://d.kontol.online/api/imageV2/i/2246211/28.jpg",
          "w": 1280,
          "h": 1920
        },
        {
          "t": "https://a.kontol.online/api/imageV2/i/2246211/29.jpg",
          "w": 1280,
          "h": 1920
        },
        {
          "t": "https://b.kontol.online/api/imageV2/i/2246211/30.jpg",
          "w": 1280,
          "h": 1920
        },
        {
          "t": "https://c.kontol.online/api/imageV2/i/2246211/31.jpg",
          "w": 1280,
          "h": 1920
        },
        {
          "t": "https://d.kontol.online/api/imageV2/i/2246211/32.jpg",
          "w": 1280,
          "h": 1920
        },
        {
          "t": "https://a.kontol.online/api/imageV2/i/2246211/33.jpg",
          "w": 1280,
          "h": 1920
        },
        {
          "t": "https://b.kontol.online/api/imageV2/i/2246211/34.jpg",
          "w": 1280,
          "h": 1920
        },
        {
          "t": "https://c.kontol.online/api/imageV2/i/2246211/35.jpg",
          "w": 1280,
          "h": 1920
        },
        {
          "t": "https://d.kontol.online/api/imageV2/i/2246211/36.jpg",
          "w": 1280,
          "h": 1920
        },
        {
          "t": "https://a.kontol.online/api/imageV2/i/2246211/37.jpg",
          "w": 1280,
          "h": 1920
        },
        {
          "t": "https://b.kontol.online/api/imageV2/i/2246211/38.jpg",
          "w": 1280,
          "h": 1920
        },
        {
          "t": "https://c.kontol.online/api/imageV2/i/2246211/39.jpg",
          "w": 1280,
          "h": 1920
        },
        {
          "t": "https://d.kontol.online/api/imageV2/i/2246211/40.jpg",
          "w": 1280,
          "h": 1920
        },
        {
          "t": "https://a.kontol.online/api/imageV2/i/2246211/41.jpg",
          "w": 1280,
          "h": 1920
        },
        {
          "t": "https://b.kontol.online/api/imageV2/i/2246211/42.jpg",
          "w": 1280,
          "h": 1920
        },
        {
          "t": "https://c.kontol.online/api/imageV2/i/2246211/43.jpg",
          "w": 1280,
          "h": 1920
        },
        {
          "t": "https://d.kontol.online/api/imageV2/i/2246211/44.jpg",
          "w": 1280,
          "h": 1920
        },
        {
          "t": "https://a.kontol.online/api/imageV2/i/2246211/45.jpg",
          "w": 1280,
          "h": 1920
        },
        {
          "t": "https://b.kontol.online/api/imageV2/i/2246211/46.jpg",
          "w": 1280,
          "h": 1920
        },
        {
          "t": "https://c.kontol.online/api/imageV2/i/2246211/47.jpg",
          "w": 1280,
          "h": 1920
        },
        {
          "t": "https://d.kontol.online/api/imageV2/i/2246211/48.jpg",
          "w": 1280,
          "h": 1920
        },
        {
          "t": "https://a.kontol.online/api/imageV2/i/2246211/49.jpg",
          "w": 1280,
          "h": 1920
        },
        {
          "t": "https://b.kontol.online/api/imageV2/i/2246211/50.jpg",
          "w": 1280,
          "h": 1920
        },
        {
          "t": "https://c.kontol.online/api/imageV2/i/2246211/51.jpg",
          "w": 1280,
          "h": 1920
        },
        {
          "t": "https://d.kontol.online/api/imageV2/i/2246211/52.jpg",
          "w": 1280,
          "h": 1920
        },
        {
          "t": "https://a.kontol.online/api/imageV2/i/2246211/53.jpg",
          "w": 1280,
          "h": 1920
        },
        {
          "t": "https://b.kontol.online/api/imageV2/i/2246211/54.jpg",
          "w": 1280,
          "h": 1920
        },
        {
          "t": "https://c.kontol.online/api/imageV2/i/2246211/55.jpg",
          "w": 1280,
          "h": 1920
        },
        {
          "t": "https://d.kontol.online/api/imageV2/i/2246211/56.jpg",
          "w": 1280,
          "h": 1920
        },
        {
          "t": "https://a.kontol.online/api/imageV2/i/2246211/57.jpg",
          "w": 1044,
          "h": 1500
        }
      ],
      "thumbnail": {
        "t": "https://c.kontol.online/api/imageV2/t/2246211/thumb.jpg",
        "w": 350,
        "h": 525
      }
    },
    "media_id": "2246211",
    "scanlator": "",
    "upload_date": "1655165181055",
    "tags": [
      {
        "id": 1207,
        "url": "/tag/milf/",
        "name": "milf",
        "type": "tag",
        "count": 31117
      },
      {
        "id": 2937,
        "url": "/tag/big-breasts/",
        "name": "big breasts",
        "type": "tag",
        "count": 133528
      },
      {
        "id": 12227,
        "url": "/language/english/",
        "name": "english",
        "type": "language",
        "count": 93364
      },
      {
        "id": 13989,
        "url": "/tag/ahegao/",
        "name": "ahegao",
        "type": "tag",
        "count": 37628
      },
      {
        "id": 14072,
        "url": "/tag/huge-breasts/",
        "name": "huge breasts",
        "type": "tag",
        "count": 9605
      },
      {
        "id": 16828,
        "url": "/tag/hairy/",
        "name": "hairy",
        "type": "tag",
        "count": 14955
      },
      {
        "id": 17249,
        "url": "/language/translated/",
        "name": "translated",
        "type": "language",
        "count": 158249
      },
      {
        "id": 19018,
        "url": "/tag/dark-skin/",
        "name": "dark skin",
        "type": "tag",
        "count": 28754
      },
      {
        "id": 19899,
        "url": "/tag/exhibitionism/",
        "name": "exhibitionism",
        "type": "tag",
        "count": 11865
      },
      {
        "id": 20035,
        "url": "/tag/x-ray/",
        "name": "x-ray",
        "type": "tag",
        "count": 27399
      },
      {
        "id": 20905,
        "url": "/tag/full-color/",
        "name": "full color",
        "type": "tag",
        "count": 48102
      },
      {
        "id": 22942,
        "url": "/tag/incest/",
        "name": "incest",
        "type": "tag",
        "count": 35487
      },
      {
        "id": 23035,
        "url": "/tag/aunt/",
        "name": "aunt",
        "type": "tag",
        "count": 1515
      },
      {
        "id": 27473,
        "url": "/tag/mosaic-censorship/",
        "name": "mosaic censorship",
        "type": "tag",
        "count": 35397
      },
      {
        "id": 33172,
        "url": "/category/doujinshi/",
        "name": "doujinshi",
        "type": "category",
        "count": 295893
      },
      {
        "id": 38228,
        "url": "/group/zenmai-kourogi/",
        "name": "zenmai kourogi",
        "type": "group",
        "count": 106
      },
      {
        "id": 90671,
        "url": "/parody/original/",
        "name": "original",
        "type": "parody",
        "count": 48405
      }
    ],
    "num_pages": 57,
    "num_favorites": 0,
    "upload_time": "1655165181055",
    "hits": 501,
    "_id": 406924,
    "lang": "english",
    "related": []
  }
}